Classfile /E:/LTS/asmjson/build/classes/java/test/com/lowtechsoft/transfer/model/HospitalInfo.class
  Last modified 2023-5-25; size 1470 bytes
  MD5 checksum f16386e753e7a56fb7cb8ecc796ed6c7
  Compiled from "HospitalInfo.java"
public class com.lowtechsoft.transfer.model.HospitalInfo extends com.lowtechsoft.transfer.model.OrgInfo
  minor version: 0
  major version: 52
  flags: ACC_PUBLIC, ACC_SUPER
Constant pool:
   #1 = Methodref          #6.#39         // com/lowtechsoft/transfer/model/OrgInfo."<init>":()V
   #2 = Fieldref           #5.#40         // com/lowtechsoft/transfer/model/HospitalInfo.level:Ljava/lang/String;
   #3 = Fieldref           #5.#41         // com/lowtechsoft/transfer/model/HospitalInfo.director:Lcom/lowtechsoft/transfer/model/DoctorInfo;
   #4 = Fieldref           #5.#42         // com/lowtechsoft/transfer/model/HospitalInfo.departments:Ljava/util/List;
   #5 = Class              #43            // com/lowtechsoft/transfer/model/HospitalInfo
   #6 = Class              #44            // com/lowtechsoft/transfer/model/OrgInfo
   #7 = Utf8               level
   #8 = Utf8               Ljava/lang/String;
   #9 = Utf8               director
  #10 = Utf8               Lcom/lowtechsoft/transfer/model/DoctorInfo;
  #11 = Utf8               departments
  #12 = Utf8               Ljava/util/List;
  #13 = Utf8               Signature
  #14 = Utf8               Ljava/util/List<Lcom/lowtechsoft/transfer/model/DeptInfo;>;
  #15 = Utf8               <init>
  #16 = Utf8               ()V
  #17 = Utf8               Code
  #18 = Utf8               LineNumberTable
  #19 = Utf8               LocalVariableTable
  #20 = Utf8               this
  #21 = Utf8               Lcom/lowtechsoft/transfer/model/HospitalInfo;
  #22 = Utf8               getLevel
  #23 = Utf8               ()Ljava/lang/String;
  #24 = Utf8               setLevel
  #25 = Utf8               (Ljava/lang/String;)V
  #26 = Utf8               getDirector
  #27 = Utf8               ()Lcom/lowtechsoft/transfer/model/DoctorInfo;
  #28 = Utf8               setDirector
  #29 = Utf8               (Lcom/lowtechsoft/transfer/model/DoctorInfo;)V
  #30 = Utf8               getDepartments
  #31 = Utf8               ()Ljava/util/List;
  #32 = Utf8               ()Ljava/util/List<Lcom/lowtechsoft/transfer/model/DeptInfo;>;
  #33 = Utf8               setDepartments
  #34 = Utf8               (Ljava/util/List;)V
  #35 = Utf8               LocalVariableTypeTable
  #36 = Utf8               (Ljava/util/List<Lcom/lowtechsoft/transfer/model/DeptInfo;>;)V
  #37 = Utf8               SourceFile
  #38 = Utf8               HospitalInfo.java
  #39 = NameAndType        #15:#16        // "<init>":()V
  #40 = NameAndType        #7:#8          // level:Ljava/lang/String;
  #41 = NameAndType        #9:#10         // director:Lcom/lowtechsoft/transfer/model/DoctorInfo;
  #42 = NameAndType        #11:#12        // departments:Ljava/util/List;
  #43 = Utf8               com/lowtechsoft/transfer/model/HospitalInfo
  #44 = Utf8               com/lowtechsoft/transfer/model/OrgInfo
{
  private java.lang.String level;
    descriptor: Ljava/lang/String;
    flags: ACC_PRIVATE

  private com.lowtechsoft.transfer.model.DoctorInfo director;
    descriptor: Lcom/lowtechsoft/transfer/model/DoctorInfo;
    flags: ACC_PRIVATE

  private java.util.List<com.lowtechsoft.transfer.model.DeptInfo> departments;
    descriptor: Ljava/util/List;
    flags: ACC_PRIVATE
    Signature: #14                          // Ljava/util/List<Lcom/lowtechsoft/transfer/model/DeptInfo;>;

  public com.lowtechsoft.transfer.model.HospitalInfo();
    descriptor: ()V
    flags: ACC_PUBLIC
    Code:
      stack=1, locals=1, args_size=1
         0: aload_0
         1: invokespecial #1                  // Method com/lowtechsoft/transfer/model/OrgInfo."<init>":()V
         4: return
      LineNumberTable:
        line 5: 0
      LocalVariableTable:
        Start  Length  Slot  Name   Signature
            0       5     0  this   Lcom/lowtechsoft/transfer/model/HospitalInfo;

  public java.lang.String getLevel();
    descriptor: ()Ljava/lang/String;
    flags: ACC_PUBLIC
    Code:
      stack=1, locals=1, args_size=1
         0: aload_0
         1: getfield      #2                  // Field level:Ljava/lang/String;
         4: areturn
      LineNumberTable:
        line 14: 0
      LocalVariableTable:
        Start  Length  Slot  Name   Signature
            0       5     0  this   Lcom/lowtechsoft/transfer/model/HospitalInfo;

  public void setLevel(java.lang.String);
    descriptor: (Ljava/lang/String;)V
    flags: ACC_PUBLIC
    Code:
      stack=2, locals=2, args_size=2
         0: aload_0
         1: aload_1
         2: putfield      #2                  // Field level:Ljava/lang/String;
         5: return
      LineNumberTable:
        line 18: 0
        line 19: 5
      LocalVariableTable:
        Start  Length  Slot  Name   Signature
            0       6     0  this   Lcom/lowtechsoft/transfer/model/HospitalInfo;
            0       6     1 level   Ljava/lang/String;

  public com.lowtechsoft.transfer.model.DoctorInfo getDirector();
    descriptor: ()Lcom/lowtechsoft/transfer/model/DoctorInfo;
    flags: ACC_PUBLIC
    Code:
      stack=1, locals=1, args_size=1
         0: aload_0
         1: getfield      #3                  // Field director:Lcom/lowtechsoft/transfer/model/DoctorInfo;
         4: areturn
      LineNumberTable:
        line 22: 0
      LocalVariableTable:
        Start  Length  Slot  Name   Signature
            0       5     0  this   Lcom/lowtechsoft/transfer/model/HospitalInfo;

  public void setDirector(com.lowtechsoft.transfer.model.DoctorInfo);
    descriptor: (Lcom/lowtechsoft/transfer/model/DoctorInfo;)V
    flags: ACC_PUBLIC
    Code:
      stack=2, locals=2, args_size=2
         0: aload_0
         1: aload_1
         2: putfield      #3                  // Field director:Lcom/lowtechsoft/transfer/model/DoctorInfo;
         5: return
      LineNumberTable:
        line 26: 0
        line 27: 5
      LocalVariableTable:
        Start  Length  Slot  Name   Signature
            0       6     0  this   Lcom/lowtechsoft/transfer/model/HospitalInfo;
            0       6     1 director   Lcom/lowtechsoft/transfer/model/DoctorInfo;

  public java.util.List<com.lowtechsoft.transfer.model.DeptInfo> getDepartments();
    descriptor: ()Ljava/util/List;
    flags: ACC_PUBLIC
    Code:
      stack=1, locals=1, args_size=1
         0: aload_0
         1: getfield      #4                  // Field departments:Ljava/util/List;
         4: areturn
      LineNumberTable:
        line 30: 0
      LocalVariableTable:
        Start  Length  Slot  Name   Signature
            0       5     0  this   Lcom/lowtechsoft/transfer/model/HospitalInfo;
    Signature: #32                          // ()Ljava/util/List<Lcom/lowtechsoft/transfer/model/DeptInfo;>;

  public void setDepartments(java.util.List<com.lowtechsoft.transfer.model.DeptInfo>);
    descriptor: (Ljava/util/List;)V
    flags: ACC_PUBLIC
    Code:
      stack=2, locals=2, args_size=2
         0: aload_0
         1: aload_1
         2: putfield      #4                  // Field departments:Ljava/util/List;
         5: return
      LineNumberTable:
        line 34: 0
        line 35: 5
      LocalVariableTable:
        Start  Length  Slot  Name   Signature
            0       6     0  this   Lcom/lowtechsoft/transfer/model/HospitalInfo;
            0       6     1 departments   Ljava/util/List;
      LocalVariableTypeTable:
        Start  Length  Slot  Name   Signature
            0       6     1 departments   Ljava/util/List<Lcom/lowtechsoft/transfer/model/DeptInfo;>;
    Signature: #36                          // (Ljava/util/List<Lcom/lowtechsoft/transfer/model/DeptInfo;>;)V
}
SourceFile: "HospitalInfo.java"
